{
  "movieInfoResult": {
    "movieInfo": {
      "movieCd": "20209137",
      "movieNm": "종착역",
      "movieNmEn": "Short Vacation",
      "movieNmOg": "",
      "showTm": "79",
      "prdtYear": "2020",
      "openDt": "20210923",
      "prdtStatNm": "개봉",
      "typeNm": "장편",
      "nations": [
        {
          "nationNm": "한국"
        }
      ],
      "genres": [
        {
          "genreNm": "드라마"
        }
      ],
      "directors": [
        {
          "peopleNm": "서한솔",
          "peopleNmEn": "SEO Han-sol"
        },
        {
          "peopleNm": "권민표",
          "peopleNmEn": "KWON Min-pyo"
        }
      ],
      "actors": [
        {
          "peopleNm": "설시연",
          "peopleNmEn": "",
          "cast": "",
          "castEn": ""
        },
        {
          "peopleNm": "배연우",
          "peopleNmEn": "BAE Yeon-woo",
          "cast": "",
          "castEn": ""
        },
        {
          "peopleNm": "박소정",
          "peopleNmEn": "",
          "cast": "",
          "castEn": ""
        },
        {
          "peopleNm": "한송희",
          "peopleNmEn": "",
          "cast": "",
          "castEn": ""
        },
        {
          "peopleNm": "강석원",
          "peopleNmEn": "",
          "cast": "",
          "castEn": ""
        },
        {
          "peopleNm": "기진우",
          "peopleNmEn": "",
          "cast": "",
          "castEn": ""
        },
        {
          "peopleNm": "김보예",
          "peopleNmEn": "",
          "cast": "",
          "castEn": ""
        },
        {
          "peopleNm": "김나경",
          "peopleNmEn": "",
          "cast": "",
          "castEn": ""
        }
      ],
      "showTypes": [
        {
          "showTypeGroupNm": "2D",
          "showTypeNm": "디지털"
        },
        {
          "showTypeGroupNm": "2D",
          "showTypeNm": "디지털 영문자막"
        }
      ],
      "companys": [
        {
          "companyCd": "20125955",
          "companyNm": "(주)타이거시네마",
          "companyNmEn": "Tiger Cinema",
          "companyPartNm": "제작사"
        },
        {
          "companyCd": "20158092",
          "companyNm": "DGC",
          "companyNmEn": "",
          "companyPartNm": "제작사"
        },
        {
          "companyCd": "20188381",
          "companyNm": "필름다빈",
          "companyNmEn": "FILM DABIN",
          "companyPartNm": "배급사"
        },
        {
          "companyCd": "20242763",
          "companyNm": "(사)한국농아인협회",
          "companyNmEn": "",
          "companyPartNm": "가치봄 제작처"
        },
        {
          "companyCd": "20242764",
          "companyNm": "한국시각장애인연합회",
          "companyNmEn": "",
          "companyPartNm": "가치봄 제작처"
        }
      ],
      "audits": [
        {
          "auditNo": "2021-MF01544",
          "watchGradeNm": "전체관람가"
        }
      ],
      "staffs": [
        {
          "peopleNm": "서한솔",
          "peopleNmEn": "SEO Han-sol",
          "staffRoleNm": "시나리오(각본)"
        },
        {
          "peopleNm": "윤원규",
          "peopleNmEn": "",
          "staffRoleNm": "제작팀"
        },
        {
          "peopleNm": "박봉수",
          "peopleNmEn": "PARK Bong-su",
          "staffRoleNm": "프로듀서"
        },
        {
          "peopleNm": "한동헌",
          "peopleNmEn": "",
          "staffRoleNm": "프로듀서"
        },
        {
          "peopleNm": "안현도",
          "peopleNmEn": "",
          "staffRoleNm": "사운드믹싱"
        },
        {
          "peopleNm": "장수민",
          "peopleNmEn": "",
          "staffRoleNm": "사운드믹싱"
        },
        {
          "peopleNm": "권민표",
          "peopleNmEn": "KWON Min-pyo",
          "staffRoleNm": "편집"
        },
        {
          "peopleNm": "서한솔",
          "peopleNmEn": "SEO Han-sol",
          "staffRoleNm": "편집"
        },
        {
          "peopleNm": "이다연",
          "peopleNmEn": "",
          "staffRoleNm": "동시녹음팀"
        },
        {
          "peopleNm": "이세현",
          "peopleNmEn": "",
          "staffRoleNm": "동시녹음팀"
        },
        {
          "peopleNm": "박가연",
          "peopleNmEn": "",
          "staffRoleNm": "동시녹음"
        },
        {
          "peopleNm": "김동익",
          "peopleNmEn": "KIM Dong-ik",
          "staffRoleNm": "촬영팀"
        },
        {
          "peopleNm": "조영준",
          "peopleNmEn": "",
          "staffRoleNm": "촬영팀"
        },
        {
          "peopleNm": "박재만",
          "peopleNmEn": "",
          "staffRoleNm": "촬영"
        },
        {
          "peopleNm": "지민정",
          "peopleNmEn": "",
          "staffRoleNm": "스크립터"
        },
        {
          "peopleNm": "성지은",
          "peopleNmEn": "",
          "staffRoleNm": "연출팀"
        },
        {
          "peopleNm": "조희원",
          "peopleNmEn": "",
          "staffRoleNm": "조감독"
        },
        {
          "peopleNm": "권민표",
          "peopleNmEn": "KWON Min-pyo",
          "staffRoleNm": "시나리오(각본)"
        },
        {
          "peopleNm": "주아람",
          "peopleNmEn": "Rachel Joo",
          "staffRoleNm": "배급진행"
        },
        {
          "peopleNm": "손민경",
          "peopleNmEn": "Michelle SON",
          "staffRoleNm": "배급진행"
        },
        {
          "peopleNm": "이나현",
          "peopleNmEn": "",
          "staffRoleNm": "배급진행"
        },
        {
          "peopleNm": "이나경",
          "peopleNmEn": "LEE Na-kyung",
          "staffRoleNm": "배급진행"
        },
        {
          "peopleNm": "문입생",
          "peopleNmEn": "",
          "staffRoleNm": "배급진행"
        },
        {
          "peopleNm": "채소라",
          "peopleNmEn": "",
          "staffRoleNm": "배급진행"
        },
        {
          "peopleNm": "박혜진",
          "peopleNmEn": "",
          "staffRoleNm": "배급진행"
        },
        {
          "peopleNm": "장예원",
          "peopleNmEn": "",
          "staffRoleNm": "배급진행"
        },
        {
          "peopleNm": "성윤지",
          "peopleNmEn": "",
          "staffRoleNm": "배급진행"
        },
        {
          "peopleNm": "권민표",
          "peopleNmEn": "KWON Min-pyo",
          "staffRoleNm": "예고편"
        },
        {
          "peopleNm": "서한솔",
          "peopleNmEn": "SEO Han-sol",
          "staffRoleNm": "예고편"
        },
        {
          "peopleNm": "박재호",
          "peopleNmEn": "PARK Jae-ho",
          "staffRoleNm": "광고디자인"
        },
        {
          "peopleNm": "이유희",
          "peopleNmEn": "LEE Yu-hee",
          "staffRoleNm": "광고디자인"
        },
        {
          "peopleNm": "이서연",
          "peopleNmEn": "",
          "staffRoleNm": "광고디자인"
        },
        {
          "peopleNm": "홍인서",
          "peopleNmEn": "",
          "staffRoleNm": "광고디자인"
        },
        {
          "peopleNm": "박인혜",
          "peopleNmEn": "",
          "staffRoleNm": "광고디자인"
        },
        {
          "peopleNm": "배기정",
          "peopleNmEn": "",
          "staffRoleNm": "온라인마케팅"
        },
        {
          "peopleNm": "유병주",
          "peopleNmEn": "",
          "staffRoleNm": "온라인마케팅"
        },
        {
          "peopleNm": "류원열",
          "peopleNmEn": "",
          "staffRoleNm": "온라인마케팅"
        },
        {
          "peopleNm": "구수연",
          "peopleNmEn": "",
          "staffRoleNm": "온라인마케팅"
        },
        {
          "peopleNm": "장하윤",
          "peopleNmEn": "",
          "staffRoleNm": "온라인마케팅"
        },
        {
          "peopleNm": "김수연",
          "peopleNmEn": "",
          "staffRoleNm": "온라인마케팅"
        },
        {
          "peopleNm": "다빈",
          "peopleNmEn": "Dabin",
          "staffRoleNm": "배급진행"
        },
        {
          "peopleNm": "최아름",
          "peopleNmEn": "",
          "staffRoleNm": "홍보/마케팅 진행"
        },
        {
          "peopleNm": "차한비",
          "peopleNmEn": "",
          "staffRoleNm": "홍보/마케팅 진행"
        },
        {
          "peopleNm": "박재만",
          "peopleNmEn": "",
          "staffRoleNm": "DI팀"
        },
        {
          "peopleNm": "이다혜",
          "peopleNmEn": "",
          "staffRoleNm": "온라인마케팅"
        }
      ]
    }
  }
}