{
  "movieInfoResult": {
    "movieInfo": {
      "movieCd": "20205200",
      "movieNm": "빛의 아버지: 파이널 판타지 XIV",
      "movieNmEn": "Brave Father Online - our story of FINAL FANTASY XIV",
      "movieNmOg": "劇場版 ファイナルファンタジーXIV 光のお父さん",
      "showTm": "114",
      "prdtYear": "2019",
      "openDt": "20210114",
      "prdtStatNm": "개봉",
      "typeNm": "장편",
      "nations": [
        {
          "nationNm": "일본"
        }
      ],
      "genres": [
        {
          "genreNm": "드라마"
        }
      ],
      "directors": [
        {
          "peopleNm": "노구치 테루오",
          "peopleNmEn": "Teruo Noguchi"
        },
        {
          "peopleNm": "야마모토 키요시",
          "peopleNmEn": "Kiyoshi Yamamoto"
        }
      ],
      "actors": [
        {
          "peopleNm": "사카구치 켄타로",
          "peopleNmEn": "Sakaguchi Kentaro",
          "cast": "",
          "castEn": ""
        },
        {
          "peopleNm": "요시다 코타로",
          "peopleNmEn": "Kotaro Yoshida",
          "cast": "",
          "castEn": ""
        },
        {
          "peopleNm": "사토 류타",
          "peopleNmEn": "Ryuta Sato",
          "cast": "",
          "castEn": ""
        }
      ],
      "showTypes": [
        {
          "showTypeGroupNm": "2D",
          "showTypeNm": "디지털"
        }
      ],
      "companys": [
        {
          "companyCd": "20158370",
          "companyNm": "(주)디스테이션",
          "companyNmEn": "",
          "companyPartNm": "배급사"
        },
        {
          "companyCd": "20139757",
          "companyNm": "(주)엔케이컨텐츠",
          "companyNmEn": "",
          "companyPartNm": "수입사"
        }
      ],
      "audits": [
        {
          "auditNo": "2020-MF01624 ",
          "watchGradeNm": "전체관람가"
        }
      ],
      "staffs": []
    }
  }
}