{
  "movieInfoResult": {
    "movieInfo": {
      "movieCd": "20217852",
      "movieNm": "환상의 스킬로 만져주는 마사지녀 2",
      "movieNmEn": "",
      "movieNmOg": "",
      "showTm": "62",
      "prdtYear": "2021",
      "openDt": "20210504",
      "prdtStatNm": "개봉",
      "typeNm": "장편",
      "nations": [
        {
          "nationNm": "일본"
        }
      ],
      "genres": [
        {
          "genreNm": "성인물(에로)"
        }
      ],
      "directors": [
        {
          "peopleNm": "핫시이",
          "peopleNmEn": ""
        }
      ],
      "actors": [
        {
          "peopleNm": "아야나 리나",
          "peopleNmEn": "Rina Ayana",
          "cast": "",
          "castEn": ""
        }
      ],
      "showTypes": [
        {
          "showTypeGroupNm": "2D",
          "showTypeNm": "디지털"
        }
      ],
      "companys": [
        {
          "companyCd": "20191961",
          "companyNm": "(주)빅콘미디어",
          "companyNmEn": "Bigcon Media",
          "companyPartNm": "배급사"
        }
      ],
      "audits": [
        {
          "auditNo": "2021-MF01007",
          "watchGradeNm": "청소년관람불가"
        }
      ],
      "staffs": []
    }
  }
}