{
  "movieInfoResult": {
    "movieInfo": {
      "movieCd": "20218302",
      "movieNm": "트립 투 그리스",
      "movieNmEn": "The Trip to Greece",
      "movieNmOg": "",
      "showTm": "103",
      "prdtYear": "2020",
      "openDt": "20210708",
      "prdtStatNm": "개봉",
      "typeNm": "장편",
      "nations": [
        {
          "nationNm": "영국"
        }
      ],
      "genres": [
        {
          "genreNm": "코미디"
        },
        {
          "genreNm": "드라마"
        }
      ],
      "directors": [
        {
          "peopleNm": "마이클 윈터바텀",
          "peopleNmEn": "Michael Winterbottom"
        }
      ],
      "actors": [
        {
          "peopleNm": "스티브 쿠건",
          "peopleNmEn": "Steve Coogan",
          "cast": "",
          "castEn": ""
        },
        {
          "peopleNm": "롭 브라이든",
          "peopleNmEn": "Rob Brydon",
          "cast": "",
          "castEn": ""
        }
      ],
      "showTypes": [
        {
          "showTypeGroupNm": "2D",
          "showTypeNm": "디지털"
        }
      ],
      "companys": [
        {
          "companyCd": "20061718",
          "companyNm": "찬란",
          "companyNmEn": "Challan Film",
          "companyPartNm": "배급사"
        },
        {
          "companyCd": "20216842",
          "companyNm": "(주)하이스트레인저",
          "companyNmEn": "Histranger",
          "companyPartNm": "배급사"
        },
        {
          "companyCd": "20061718",
          "companyNm": "찬란",
          "companyNmEn": "Challan Film",
          "companyPartNm": "수입사"
        },
        {
          "companyCd": "20111472",
          "companyNm": "(주)51k",
          "companyNmEn": "",
          "companyPartNm": "공동제공"
        }
      ],
      "audits": [
        {
          "auditNo": "2021-MF01240",
          "watchGradeNm": "15세이상관람가"
        }
      ],
      "staffs": []
    }
  }
}