{
  "movieInfoResult": {
    "movieInfo": {
      "movieCd": "20210610",
      "movieNm": "레드 아워",
      "movieNmEn": "Red Hour",
      "movieNmOg": "Rogue Hostage",
      "showTm": "93",
      "prdtYear": "2021",
      "openDt": "20210923",
      "prdtStatNm": "개봉",
      "typeNm": "장편",
      "nations": [
        {
          "nationNm": "미국"
        }
      ],
      "genres": [
        {
          "genreNm": "액션"
        },
        {
          "genreNm": "스릴러"
        }
      ],
      "directors": [],
      "actors": [
        {
          "peopleNm": "타이레스 깁슨",
          "peopleNmEn": "Tyrese Gibson",
          "cast": "카일",
          "castEn": ""
        },
        {
          "peopleNm": "존 말코비치",
          "peopleNmEn": "John Malkovich",
          "cast": "샘",
          "castEn": ""
        }
      ],
      "showTypes": [
        {
          "showTypeGroupNm": "2D",
          "showTypeNm": "디지털"
        }
      ],
      "companys": [
        {
          "companyCd": "20141648",
          "companyNm": "(주)올스타엔터테인먼트",
          "companyNmEn": "",
          "companyPartNm": "배급사"
        },
        {
          "companyCd": "20141648",
          "companyNm": "(주)올스타엔터테인먼트",
          "companyNmEn": "",
          "companyPartNm": "수입사"
        }
      ],
      "audits": [
        {
          "auditNo": "2021-MF02230",
          "watchGradeNm": "15세이상관람가"
        }
      ],
      "staffs": []
    }
  }
}