{
  "movieInfoResult": {
    "movieInfo": {
      "movieCd": "20236535",
      "movieNm": "딱 좋게 익어버린 50대 마돈나 아줌마 무삭제판",
      "movieNmEn": "",
      "movieNmOg": "",
      "showTm": "83",
      "prdtYear": "2023",
      "openDt": "20231221",
      "prdtStatNm": "기타",
      "typeNm": "장편",
      "nations": [
        {
          "nationNm": "일본"
        }
      ],
      "genres": [
        {
          "genreNm": "성인물(에로)"
        }
      ],
      "directors": [],
      "actors": [],
      "showTypes": [
        {
          "showTypeGroupNm": "2D",
          "showTypeNm": "디지털"
        }
      ],
      "companys": [],
      "audits": [
        {
          "auditNo": "2023-MF03374",
          "watchGradeNm": "청소년관람불가"
        }
      ],
      "staffs": []
    },
    "source": "영화진흥위원회"
  }
}