{
  "movieInfoResult": {
    "movieInfo": {
      "movieCd": "20236146",
      "movieNm": "신차원! 짱구는 못말려 더 무비 초능력 대결전 ~날아라 수제김밥~",
      "movieNmEn": "New Dimension! Crayon Shinchan the Movie: Battle of Supernatural Powers ~Flying Sushi~",
      "movieNmOg": "しん次元！クレヨンしんちゃんTHE MOVIE: 超能力大決戦 ～とべとべ手巻き寿司～",
      "showTm": "94",
      "prdtYear": "2023",
      "openDt": "20231222",
      "prdtStatNm": "개봉",
      "typeNm": "장편",
      "nations": [
        {
          "nationNm": "일본"
        }
      ],
      "genres": [
        {
          "genreNm": "애니메이션"
        }
      ],
      "directors": [
        {
          "peopleNm": "오네 히토시",
          "peopleNmEn": "Hitoshi Ohne"
        }
      ],
      "actors": [],
      "showTypes": [
        {
          "showTypeGroupNm": "2D",
          "showTypeNm": "디지털"
        },
        {
          "showTypeGroupNm": "2D",
          "showTypeNm": "디지털 한글자막 CC"
        },
        {
          "showTypeGroupNm": "2D",
          "showTypeNm": "디지털 더빙"
        }
      ],
      "companys": [
        {
          "companyCd": "20110854",
          "companyNm": "(주)씨제이이엔엠",
          "companyNmEn": "CJ ENM Corp.",
          "companyPartNm": "배급사"
        },
        {
          "companyCd": "20110854",
          "companyNm": "(주)씨제이이엔엠",
          "companyNmEn": "CJ ENM Corp.",
          "companyPartNm": "수입사"
        },
        {
          "companyCd": "20242763",
          "companyNm": "(사)한국농아인협회",
          "companyNmEn": "",
          "companyPartNm": "가치봄 제작처"
        },
        {
          "companyCd": "20242764",
          "companyNm": "한국시각장애인연합회",
          "companyNmEn": "",
          "companyPartNm": "가치봄 제작처"
        }
      ],
      "audits": [
        {
          "auditNo": "2023-MF03167",
          "watchGradeNm": "전체관람가"
        }
      ],
      "staffs": []
    },
    "source": "영화진흥위원회"
  }
}