{
  "movieInfoResult": {
    "movieInfo": {
      "movieCd": "20212428",
      "movieNm": "되살아나는 목소리",
      "movieNmEn": "Voices of the Silenced",
      "movieNmOg": "",
      "showTm": "148",
      "prdtYear": "2023",
      "openDt": "20241113",
      "prdtStatNm": "개봉",
      "typeNm": "장편",
      "nations": [
        {
          "nationNm": "한국"
        },
        {
          "nationNm": "일본"
        }
      ],
      "genres": [
        {
          "genreNm": "다큐멘터리"
        }
      ],
      "directors": [
        {
          "peopleNm": "박마의",
          "peopleNmEn": "PARK Maeui"
        },
        {
          "peopleNm": "박수남",
          "peopleNmEn": "PARK Soo-nam"
        }
      ],
      "actors": [
        {
          "peopleNm": "박수남",
          "peopleNmEn": "PARK Soo-nam",
          "cast": "박수남",
          "castEn": "PARK Soo-nam"
        },
        {
          "peopleNm": "박마의",
          "peopleNmEn": "PARK Maeui",
          "cast": "박마의",
          "castEn": "PARK Maeui"
        }
      ],
      "showTypes": [
        {
          "showTypeGroupNm": "2D",
          "showTypeNm": "디지털"
        }
      ],
      "companys": [
        {
          "companyCd": "20242881",
          "companyNm": "영화사 하르빈",
          "companyNmEn": "",
          "companyPartNm": "제작사"
        },
        {
          "companyCd": "20123217",
          "companyNm": "(주)시네마달",
          "companyNmEn": "Cinema DAL",
          "companyPartNm": "배급사"
        },
        {
          "companyCd": "20100536",
          "companyNm": "푸른영상",
          "companyNmEn": "P.U.R.N Production",
          "companyPartNm": "배급사"
        },
        {
          "companyCd": "20123217",
          "companyNm": "(주)시네마달",
          "companyNmEn": "Cinema DAL",
          "companyPartNm": "해외세일즈사"
        }
      ],
      "audits": [
        {
          "auditNo": "2024-MF02628 ",
          "watchGradeNm": "12세이상관람가"
        }
      ],
      "staffs": [
        {
          "peopleNm": "박마의",
          "peopleNmEn": "PARK Maeui",
          "staffRoleNm": "프로듀서"
        },
        {
          "peopleNm": "박마의",
          "peopleNmEn": "PARK Maeui",
          "staffRoleNm": "촬영"
        },
        {
          "peopleNm": "박수남",
          "peopleNmEn": "PARK Soo-nam",
          "staffRoleNm": "촬영"
        },
        {
          "peopleNm": "조영은",
          "peopleNmEn": "",
          "staffRoleNm": "홍보/마케팅 진행"
        }
      ]
    },
    "source": "영화진흥위원회"
  }
}