{
  "movieInfoResult": {
    "movieInfo": {
      "movieCd": "20235921",
      "movieNm": "힙노시스: LP 커버의 전설",
      "movieNmEn": "Squaring the Circle: The Story of Hipgnosis",
      "movieNmOg": "",
      "showTm": "100",
      "prdtYear": "2022",
      "openDt": "20240501",
      "prdtStatNm": "개봉",
      "typeNm": "장편",
      "nations": [
        {
          "nationNm": "영국"
        }
      ],
      "genres": [
        {
          "genreNm": "다큐멘터리"
        }
      ],
      "directors": [
        {
          "peopleNm": "안톤 코르빈",
          "peopleNmEn": "Anton Corbijn"
        }
      ],
      "actors": [
        {
          "peopleNm": "오브리 파월",
          "peopleNmEn": "Aubrey Powell",
          "cast": "",
          "castEn": ""
        },
        {
          "peopleNm": "스톰 소거슨",
          "peopleNmEn": "Storm Thorgerson",
          "cast": "",
          "castEn": ""
        },
        {
          "peopleNm": "폴 매카트니",
          "peopleNmEn": "Paul McCartney",
          "cast": "",
          "castEn": ""
        },
        {
          "peopleNm": "데이비드 길모어",
          "peopleNmEn": "David Gilmour",
          "cast": "",
          "castEn": ""
        },
        {
          "peopleNm": "로저 워터스",
          "peopleNmEn": "Roger Waters",
          "cast": "",
          "castEn": ""
        },
        {
          "peopleNm": "닉 메이슨",
          "peopleNmEn": "Nick Mason",
          "cast": "",
          "castEn": ""
        },
        {
          "peopleNm": "지미 페이지",
          "peopleNmEn": "Jimmy Page",
          "cast": "",
          "castEn": ""
        },
        {
          "peopleNm": "로버트 플랜트",
          "peopleNmEn": "Robert Plant",
          "cast": "",
          "castEn": ""
        },
        {
          "peopleNm": "노엘 갤러거",
          "peopleNmEn": "Noel Gallagher",
          "cast": "",
          "castEn": ""
        },
        {
          "peopleNm": "피터 가브리엘",
          "peopleNmEn": "Peter Gabriel",
          "cast": "",
          "castEn": ""
        },
        {
          "peopleNm": "그레이엄 굴드먼",
          "peopleNmEn": "Graham Gouldman",
          "cast": "",
          "castEn": ""
        },
        {
          "peopleNm": "글렌 매틀록",
          "peopleNmEn": "",
          "cast": "",
          "castEn": ""
        }
      ],
      "showTypes": [
        {
          "showTypeGroupNm": "2D",
          "showTypeNm": "디지털"
        }
      ],
      "companys": [
        {
          "companyCd": "20063009",
          "companyNm": "(주)티캐스트",
          "companyNmEn": "TCast",
          "companyPartNm": "배급사"
        },
        {
          "companyCd": "20063009",
          "companyNm": "(주)티캐스트",
          "companyNmEn": "TCast",
          "companyPartNm": "수입사"
        }
      ],
      "audits": [
        {
          "auditNo": "2024-MF00185",
          "watchGradeNm": "15세이상관람가"
        }
      ],
      "staffs": [
        {
          "peopleNm": "콜린 퍼스",
          "peopleNmEn": "Colin Firth",
          "staffRoleNm": "제작"
        }
      ]
    },
    "source": "영화진흥위원회"
  }
}