{
  "movieInfoResult": {
    "movieInfo": {
      "movieCd": "20247944",
      "movieNm": "스텔라",
      "movieNmEn": "Stella. A Life.",
      "movieNmOg": "",
      "showTm": "120",
      "prdtYear": "2023",
      "openDt": "20240522",
      "prdtStatNm": "개봉",
      "typeNm": "장편",
      "nations": [
        {
          "nationNm": "독일"
        }
      ],
      "genres": [
        {
          "genreNm": "드라마"
        }
      ],
      "directors": [],
      "actors": [],
      "showTypes": [
        {
          "showTypeGroupNm": "2D",
          "showTypeNm": "디지털"
        }
      ],
      "companys": [
        {
          "companyCd": "20139140",
          "companyNm": "(주)뮤제엔터테인먼트",
          "companyNmEn": "",
          "companyPartNm": "배급사"
        },
        {
          "companyCd": "20100048",
          "companyNm": "미디어소프트",
          "companyNmEn": "",
          "companyPartNm": "수입사"
        }
      ],
      "audits": [
        {
          "auditNo": "2024-MF00337 ",
          "watchGradeNm": "15세이상관람가"
        }
      ],
      "staffs": []
    },
    "source": "영화진흥위원회"
  }
}