{
  "movieInfoResult": {
    "movieInfo": {
      "movieCd": "20256101",
      "movieNm": "마지막 숙제",
      "movieNmEn": "",
      "movieNmOg": "",
      "showTm": "108",
      "prdtYear": "2025",
      "openDt": "20250903",
      "prdtStatNm": "개봉예정",
      "typeNm": "장편",
      "nations": [
        {
          "nationNm": "한국"
        }
      ],
      "genres": [
        {
          "genreNm": "드라마"
        }
      ],
      "directors": [
        {
          "peopleNm": "이정철",
          "peopleNmEn": "LEE Jung-chul"
        }
      ],
      "actors": [
        {
          "peopleNm": "엄태웅",
          "peopleNmEn": "UHM Tae-woong",
          "cast": "",
          "castEn": ""
        },
        {
          "peopleNm": "박상면",
          "peopleNmEn": "PARK Sang-myun",
          "cast": "",
          "castEn": ""
        },
        {
          "peopleNm": "이재준",
          "peopleNmEn": "",
          "cast": "",
          "castEn": ""
        },
        {
          "peopleNm": "최이나",
          "peopleNmEn": "",
          "cast": "곽정은",
          "castEn": ""
        },
        {
          "peopleNm": "윤현숙",
          "peopleNmEn": "",
          "cast": "",
          "castEn": ""
        },
        {
          "peopleNm": "정선우",
          "peopleNmEn": "",
          "cast": "정민호",
          "castEn": ""
        },
        {
          "peopleNm": "이성종",
          "peopleNmEn": "",
          "cast": "",
          "castEn": ""
        },
        {
          "peopleNm": "전수경",
          "peopleNmEn": "",
          "cast": "",
          "castEn": ""
        }
      ],
      "showTypes": [
        {
          "showTypeGroupNm": "2D",
          "showTypeNm": "디지털"
        }
      ],
      "companys": [
        {
          "companyCd": "20254381",
          "companyNm": "(주)스튜디오킬러웨일",
          "companyNmEn": "STUDIO KILLERWHALE",
          "companyPartNm": "제작사"
        },
        {
          "companyCd": "20253445",
          "companyNm": "(주)코끼리이엔티",
          "companyNmEn": "",
          "companyPartNm": "공동제작사"
        },
        {
          "companyCd": "20242743",
          "companyNm": "(주)에스더블유콘텐츠",
          "companyNmEn": "",
          "companyPartNm": "공동제작사"
        },
        {
          "companyCd": "20141848",
          "companyNm": "(주)이놀미디어",
          "companyNmEn": "",
          "companyPartNm": "배급사"
        },
        {
          "companyCd": "20254381",
          "companyNm": "(주)스튜디오킬러웨일",
          "companyNmEn": "STUDIO KILLERWHALE",
          "companyPartNm": "배급사"
        },
        {
          "companyCd": "20242743",
          "companyNm": "(주)에스더블유콘텐츠",
          "companyNmEn": "",
          "companyPartNm": "배급사"
        },
        {
          "companyCd": "20254381",
          "companyNm": "(주)스튜디오킬러웨일",
          "companyNmEn": "STUDIO KILLERWHALE",
          "companyPartNm": "제공"
        },
        {
          "companyCd": "20242743",
          "companyNm": "(주)에스더블유콘텐츠",
          "companyNmEn": "",
          "companyPartNm": "제공"
        }
      ],
      "audits": [
        {
          "auditNo": "2025-MF01904 ",
          "watchGradeNm": "12세이상관람가"
        }
      ],
      "staffs": [
        {
          "peopleNm": "장규성",
          "peopleNmEn": "JANG Kyu-sung",
          "staffRoleNm": "제작"
        },
        {
          "peopleNm": "최석환",
          "peopleNmEn": "CHOI Suk-hwan",
          "staffRoleNm": "시나리오(각본)"
        },
        {
          "peopleNm": "이민호",
          "peopleNmEn": "Min-ho LEE",
          "staffRoleNm": "제작"
        }
      ]
    },
    "source": "영화진흥위원회"
  }
}