{
  "movieInfoResult": {
    "movieInfo": {
      "movieCd": "20241109",
      "movieNm": "블러디 이스케이프: 지옥의 도주극",
      "movieNmEn": "BLOODY ESCAPE",
      "movieNmOg": "BLOODY ESCAPE -地獄の逃走劇-",
      "showTm": "97",
      "prdtYear": "2024",
      "openDt": "20240725",
      "prdtStatNm": "개봉",
      "typeNm": "장편",
      "nations": [
        {
          "nationNm": "일본"
        }
      ],
      "genres": [
        {
          "genreNm": "애니메이션"
        }
      ],
      "directors": [
        {
          "peopleNm": "타니구치 고로",
          "peopleNmEn": "Goro Taniguchi"
        }
      ],
      "actors": [],
      "showTypes": [
        {
          "showTypeGroupNm": "2D",
          "showTypeNm": "디지털"
        }
      ],
      "companys": [
        {
          "companyCd": "20141088",
          "companyNm": "와이드 릴리즈(주)",
          "companyNmEn": "Wide Release",
          "companyPartNm": "배급사"
        },
        {
          "companyCd": "20062868",
          "companyNm": "(주)도키엔터테인먼트",
          "companyNmEn": "",
          "companyPartNm": "수입사"
        }
      ],
      "audits": [
        {
          "auditNo": "2024-MF01086 ",
          "watchGradeNm": "15세이상관람가"
        }
      ],
      "staffs": []
    },
    "source": "영화진흥위원회"
  }
}